summaryxtract/__init__.py
summaryxtract/main.py
summaryxtract/prompts.py
summaryxtract-2025.12.21153710.dist-info/METADATA
summaryxtract-2025.12.21153710.dist-info/WHEEL
summaryxtract-2025.12.21153710.dist-info/top_level.txt
summaryxtract-2025.12.21153710.dist-info/RECORD
