Metadata-Version: 2.4
Name: summaryxtract
Version: 2025.12.21153710
Summary: A new package is designed to facilitate structured, reliable extraction of key insights from user-provided texts about cultural topics. It accepts a text input, such as an article or discussion prompt
Author-email: summaryxtract <hi@eugene.plus>
License: MIT
Project-URL: Homepage, https://github.com/chigwell/summaryxtract
Requires-Python: >=3.9
Requires-Dist: langchain-llm7>=0.0.0
Requires-Dist: llmatch-messages>=0.0.0
Requires-Dist: langchain-core>=0.3.0
